Metadata-Version: 2.1
Name: scalefree-target-s3-json
Version: 0.2
Summary: Singer.io target for writing JSON files and upload to S3
Home-page: https://github.com/ScalefreeCOM/scalefree-target-s3-json
Author: Scalefree GmbH
License: UNKNOWN
Download-URL: https://github.com/ScalefreeCOM/scalefree-target-s3-json/archive/refs/tags/v_02.tar.gz
Platform: UNKNOWN
Classifier: License :: OSI Approved :: Apache Software License
Classifier: Programming Language :: Python :: 3 :: Only
Provides-Extra: test
